_eos.cpython-312-aarch64-linux-gnu.so
_eos_data/references.yaml
_eos_data/constraints/B-to-D-l-nu.yaml
_eos_data/constraints/B-to-D-pi-l-nu.yaml
_eos_data/constraints/B-to-K-charmonium.yaml
_eos_data/constraints/B-to-K-ll.yaml
_eos_data/constraints/B-to-Kstar-charmonium.yaml
_eos_data/constraints/B-to-Kstar-gamma.yaml
_eos_data/constraints/B-to-Kstar-ll.yaml
_eos_data/constraints/B-to-P-P-form-factors.yaml
_eos_data/constraints/B-to-P-form-factors.yaml
_eos_data/constraints/B-to-V-form-factors.yaml
_eos_data/constraints/B-to-Xs-gamma.yaml
_eos_data/constraints/B-to-Xs-ll.yaml
_eos_data/constraints/B-to-eta-l-nu.yaml
_eos_data/constraints/B-to-omega-l-nu.yaml
_eos_data/constraints/B-to-pi-l-nu.yaml
_eos_data/constraints/B-to-pi-pi-l-nu.yaml
_eos_data/constraints/B-to-psd-psd.yaml
_eos_data/constraints/B-to-rho-l-nu.yaml
_eos_data/constraints/Bq-to-Dq-P.yaml
_eos_data/constraints/Bq-to-dilepton.yaml
_eos_data/constraints/Bs-to-Ds-gamma-l-nu.yaml
_eos_data/constraints/Bs-to-Ds-l-nu.yaml
_eos_data/constraints/Bs-to-phi-charmonium.yaml
_eos_data/constraints/Bs-to-phi-ll.yaml
_eos_data/constraints/D-to-K-l-nu.yaml
_eos_data/constraints/D-to-P-form-factors.yaml
_eos_data/constraints/D-to-eta-l-nu.yaml
_eos_data/constraints/Dq-to-dilepton.yaml
_eos_data/constraints/Ds-to-eta-l-nu.yaml
_eos_data/constraints/K-to-l-nu.yaml
_eos_data/constraints/K-to-pi-l-nu.yaml
_eos_data/constraints/Lb-to-L-ll.yaml
_eos_data/constraints/Lb-to-Lq-form-factors.yaml
_eos_data/constraints/Lc-to-L-form-factors.yaml
_eos_data/constraints/Lc-to-L-l-nu.yaml
_eos_data/constraints/dispersive-bounds.yaml
_eos_data/constraints/ee-to-ccbar.yaml
_eos_data/constraints/ee-to-pipi.yaml
_eos_data/constraints/epi-to-epi.yaml
_eos_data/constraints/miscellaneous.yaml
_eos_data/constraints/tau-to-K-nu.yaml
_eos_data/constraints/tau-to-K-pi-nu.yaml
_eos_data/constraints/tau-to-pi-pi-nu.yaml
_eos_data/constraints/wet-constraints.yaml
eoshep-1.0.18.dist-info/METADATA
eoshep-1.0.18.dist-info/WHEEL
eoshep-1.0.18.dist-info/top_level.txt
eoshep-1.0.18.dist-info/RECORD
