Metadata-Version: 2.4
Name: eoshep
Version: 1.0.18
Summary: EOS -- A HEP program for Flavor Observables
Home-page: https://eos.github.io/
Author: Danny van Dyk and others
Author-email: danny.van.dyk@gmail.com
License: GPLv2
Classifier: Intended Audience :: Science/Research
Classifier: License :: OSI Approved :: GNU General Public License v2 (GPLv2)
Classifier: Operating System :: POSIX :: Linux
Classifier: Programming Language :: C++
Classifier: Programming Language :: Python :: 3 :: Only
Classifier: Programming Language :: Python :: Implementation :: CPython
Classifier: Topic :: Scientific/Engineering :: Physics
Requires-Python: >=3.10
Requires-Dist: argcomplete
Requires-Dist: dynesty
Requires-Dist: matplotlib
Requires-Dist: numpy>=1.13
Requires-Dist: pypandoc
Requires-Dist: pypmc>=1.1.4
Requires-Dist: pyyaml
Requires-Dist: scipy
Requires-Dist: tqdm
Dynamic: author
Dynamic: author-email
Dynamic: classifier
Dynamic: description
Dynamic: description-content-type
Dynamic: home-page
Dynamic: license
Dynamic: requires-dist
Dynamic: requires-python
Dynamic: summary
